ProxyTypes-0.10.0-py2.7-nspkg.pth
ProxyTypes-0.10.0.dist-info/DESCRIPTION.rst
ProxyTypes-0.10.0.dist-info/METADATA
ProxyTypes-0.10.0.dist-info/RECORD
ProxyTypes-0.10.0.dist-info/WHEEL
ProxyTypes-0.10.0.dist-info/metadata.json
ProxyTypes-0.10.0.dist-info/namespace_packages.txt
ProxyTypes-0.10.0.dist-info/top_level.txt
peak/util/proxies.py
