Metadata-Version: 1.0
Name: ProxyTypes
Version: 0.10.0
Summary: General purpose proxy and wrapper types
Home-page: https://github.com/PEAK-Legacy/ProxyTypes#readme
Author: Phillip J. Eby
Author-email: peak@eby-sarna.com
License: PSF or ZPL
Platform: UNKNOWN
